[
  {
    "title": "18 Herbs Hair Care Kit",
    "link": "https://pakeezaproducts.store/products/18-herbs-hair-care-kit",
    "price": "Rs.4,998.00",
    "discountedPrice": "Rs.4,500.00",
    "category": "Hair Care"
  },
  {
    "title": "18 Herbs Hair Mask 100gm",
    "link": "https://pakeezaproducts.store/products/18-herbs-hair-mask-100gm",
    "price": "Rs.1,599.00",
    "category": "Hair Care"
  },
  {
    "title": "18 Herbs Hair Mask 100gm | Pack of 2",
    "link": "https://pakeezaproducts.store/products/18-herbs-hair-mask-100gm-pack-of-2",
    "price": "Rs.3,198.00",
    "discountedPrice": "Rs.2,799.00",
    "category": "Hair Care"
  },
  {
    "title": "18 Herbs Hair Oil 100ml",
    "link": "https://pakeezaproducts.store/products/18-herbs-hair-oil-100ml",
    "price": "Rs.1,599.00",
    "category": "Hair Care"
  },
  {
    "title": "18 Herbs Hair Oil 100ml | Pack of 2",
    "link": "https://pakeezaproducts.store/products/18-herbs-hair-oil-100ml-pack-of-2",
    "price": "Rs.3,198.00",
    "discountedPrice": "Rs.2,799.00",
    "category": "Hair Care"
  },
  {
    "title": "18 Herbs Hair Shampoo 200ml",
    "link": "https://pakeezaproducts.store/products/18-herbs-hair-shampoo-200ml",
    "price": "Rs.1,800.00",
    "category": "Hair Care"
  },
  {
    "title": "18 Herbs Hair Shampoo 200ml | Pack of 2",
    "link": "https://pakeezaproducts.store/products/18-herbs-hair-shampoo-200ml-pack-of-2",
    "price": "Rs.3,600.00",
    "discountedPrice": "Rs.3,398.00",
    "category": "Hair Care"
  },
  {
    "title": "2 in 1 skin care combo",
    "link": "https://pakeezaproducts.store/products/2-in-1-skin-care-combo",
    "price": "Rs.3,298.00",
    "discountedPrice": "Rs.3,099.00",
    "category": "Skin Care"
  },
  {
    "title": "2 in 1 Skin Care pack",
    "link": "https://pakeezaproducts.store/products/2-in-1-skin-care-pack",
    "price": "Rs.3,349.00",
    "discountedPrice": "Rs.3,099.00",
    "category": "Skin Care"
  },
  {
    "title": "3 in 1 Best Hair Care kit",
    "link": "https://pakeezaproducts.store/products/3-in-1-best-hair-care-kit",
    "price": "Rs.4,450.00",
    "discountedPrice": "Rs.4,100.00",
    "category": "Hair Care"
  },
  {
    "title": "3 in 1 Anti-Aging skin care pack",
    "link": "https://pakeezaproducts.store/products/3-in-1-anti-aging-skin-care-pack",
    "price": "Rs.4,699.00",
    "discountedPrice": "Rs.4,449.00",
    "category": "Skin Care"
  },
  {
    "title": "3 in 1 Pakeeza best skin care bundle",
    "link": "https://pakeezaproducts.store/products/3-in-1-pakeeza-best-skin-care-bundle",
    "price": "Rs.4,648.00",
    "discountedPrice": "Rs.4,289.00",
    "category": "Skin Care"
  },
  {
    "title": "3 Pack Of Mouth Solution",
    "link": "https://pakeezaproducts.store/products/3-pack-of-mouth-solution",
    "price": "Rs.3,597.00",
    "discountedPrice": "Rs.3,299.00",
    "category": "Oral Care"
  },
  {
    "title": "4 in 1 Hair Care kit",
    "link": "https://pakeezaproducts.store/products/4-in-1-hair-care-kit",
    "price": "Rs.6,497.00",
    "discountedPrice": "Rs.5,799.00",
    "category": "Hair Care"
  },
  {
    "title": "Acne Face Mask 120gm",
    "link": "https://pakeezaproducts.store/products/acne-face-mask-120gm",
    "price": "Rs.1,299.00",
    "category": "Skin Care"
  },
  {
    "title": "Acne Face Mask 120gm | Pack of 2",
    "link": "https://pakeezaproducts.store/products/acne-face-mask-120gm-pack-of-2",
    "price": "Rs.2,598.00",
    "discountedPrice": "Rs.2,398.00",
    "category": "Skin Care"
  },
  {
    "title": "Acne mask with ubtan facewash | combo",
    "link": "https://pakeezaproducts.store/products/acne-mask-with-ubtan-facewash-combo",
    "price": "Rs.2,598.00",
    "discountedPrice": "Rs.2,398.00",
    "category": "Skin Care"
  },
  {
    "title": "Anti Aging Facepack with ubtan facewash | combo",
    "link": "https://pakeezaproducts.store/products/anti-aging-facepack-with-ubtan-facewash-combo",
    "price": "Rs.2,649.00",
    "discountedPrice": "Rs.2,398.00",
    "category": "Skin Care"
  },
  {
    "title": "Anti-Aging Combo",
    "link": "https://pakeezaproducts.store/products/anti-aging-combo",
    "price": "Rs.2,700.00",
    "discountedPrice": "Rs.2,398.00",
    "category": "Skin Care"
  },
  {
    "title": "Anti-Aging Face Pack 120gm",
    "link": "https://pakeezaproducts.store/products/anti-aging-face-pack-120gm",
    "price": "Rs.1,350.00",
    "category": "Skin Care"
  },
  {
    "title": "Anti-Aging Face Pack 120gm | Pack of 2",
    "link": "https://pakeezaproducts.store/products/anti-aging-face-pack-120gm-pack-of-2",
    "price": "Rs.2,698.00",
    "discountedPrice": "Rs.2,398.00",
    "category": "Skin Care"
  },
  {
    "title": "Anti-Aging Face Wash Powder 120gm",
    "link": "https://pakeezaproducts.store/products/anti-aging-face-wash-powder-120gm",
    "price": "Rs.1,350.00",
    "category": "Skin Care"
  },
  {
    "title": "Anti-Aging Face Wash Powder 120gm | Pack of 2",
    "link": "https://pakeezaproducts.store/products/anti-aging-face-wash-powder-120gm-pack-of-2",
    "price": "Rs.2,698.00",
    "discountedPrice": "Rs.2,398.00",
    "category": "Skin Care"
  },
  {
    "title": "Hair Booster Heat Protection Serum 50ml",
    "link": "https://pakeezaproducts.store/products/hair-booster-heat-protection-serum-50ml",
    "price": "Rs.1,499.00",
    "category": "Hair Care"
  },
  {
    "title": "Hair Booster Heat Protection Serum 50ml | Pack of 2",
    "link": "https://pakeezaproducts.store/products/hair-booster-heat-protection-serum-50ml-pack-of-2",
    "price": "Rs.2,998.00",
    "discountedPrice": "Rs.2,698.00",
    "category": "Hair Care"
  },
  {
    "title": "Hand Made Natural Shampoo 200ml",
    "link": "https://pakeezaproducts.store/products/hand-made-natural-shampoo-200ml",
    "price": "Rs.1,799.00",
    "category": "Hair Care"
  },
  {
    "title": "Hand Made Natural Shampoo 200ml | Pack of 2",
    "link": "https://pakeezaproducts.store/products/hand-made-natural-shampoo-200ml-pack-of-2",
    "price": "Rs.3,598.00",
    "discountedPrice": "Rs.3,398.00",
    "category": "Hair Care"
  },
  {
    "title": "Handmade Natural Shampoo 100ml",
    "link": "https://pakeezaproducts.store/products/handmade-natural-shampoo-100ml",
    "price": "Rs.999.00",
    "category": "Hair Care"
  },
  {
    "title": "Handmade Natural Shampoo 100ml | Pack of 2",
    "link": "https://pakeezaproducts.store/products/handmade-natural-shampoo-100ml-pack-of-2",
    "price": "Rs.1,998.00",
    "discountedPrice": "Rs.1,799.00",
    "category": "Hair Care"
  },
  {
    "title": "Keratin Shampoo 250ml",
    "link": "https://pakeezaproducts.store/products/keratin-shampoo-250ml",
    "price": "Rs.1,999.00",
    "category": "Hair Care"
  },
  {
    "title": "Keratin Shampoo 250ml | Pack of 2",
    "link": "https://pakeezaproducts.store/products/keratin-shampoo-250ml-pack-of-2",
    "price": "Rs.3,998.00",
    "discountedPrice": "Rs.3,599.00",
    "category": "Hair Care"
  },
  {
    "title": "Mouth Solution 50gm",
    "link": "https://pakeezaproducts.store/products/mouth-solution-50gm",
    "price": "Rs.1,199.00",
    "category": "Oral Care"
  },
  {
    "title": "Mouth Solution 50gm | Pack of 2",
    "link": "https://pakeezaproducts.store/products/mouth-solution-50gm-pack-of-2",
    "price": "Rs.2,398.00",
    "discountedPrice": "Rs.2,298.00",
    "category": "Oral Care"
  },
  {
    "title": "Noor Jahan Gift Pack",
    "link": "https://pakeezaproducts.store/products/pakeeza-skincare-gift-pack",
    "price": "Rs.7,647.00",
    "category": "Skin Care"
  },
  {
    "title": "Organic Minoxidil Hair Regrowth Solution 120ml",
    "link": "https://pakeezaproducts.store/products/organic-minoxidil-hair-regrowth-solution-120ml",
    "price": "Rs.1,249.00",
    "category": "Hair Care"
  },
  {
    "title": "Organic Minoxidil Hair Regrowth Solution 120ml | Pack of 2",
    "link": "https://pakeezaproducts.store/products/organic-minoxidil-hair-regrowth-solution-120ml-pack-of-2",
    "price": "Rs.2,498.00",
    "discountedPrice": "Rs.2,198.00",
    "category": "Hair Care"
  },
  {
    "title": "Organic Multivitamin Serum 30ml",
    "link": "https://pakeezaproducts.store/products/organic-multivitamin-serum-30ml",
    "price": "Rs.1,999.00",
    "category": "Skin Care"
  },
  {
    "title": "Organic Multivitamin Serum 30ml | Pack of 2",
    "link": "https://pakeezaproducts.store/products/organic-multivitamin-serum-30ml-pack-of-2",
    "price": "Rs.3,999.00",
    "discountedPrice": "Rs.3,599.00",
    "category": "Skin Care"
  },
  {
    "title": "Pakeeza Hair Care Kit",
    "link": "https://pakeezaproducts.store/products/pakeeza-hair-care-kit",
    "price": "Rs.6,247.00",
    "discountedPrice": "Rs.5,699.00",
    "category": "Hair Care"
  },
  {
    "title": "Pakeeza Skin Care Kit",
    "link": "https://pakeezaproducts.store/products/pakeeza-skin-care-kit",
    "price": "Rs.4,648.00",
    "discountedPrice": "Rs.4,289.00",
    "category": "Skin Care"
  },
  {
    "title": "Ubtan Face Wash Powder 120gm",
    "link": "https://pakeezaproducts.store/products/ubtan-face-wash-powder-120gm",
    "price": "Rs.1,299.00",
    "category": "Skin Care"
  },
  {
    "title": "Ubtan Face Wash Powder 120gm | Pack of 2",
    "link": "https://pakeezaproducts.store/products/ubtan-face-wash-powder-120gm-pack-of-2",
    "price": "Rs.2,598.00",
    "discountedPrice": "Rs.2,398.00",
    "category": "Skin Care"
  },
  {
    "title": "WOW Immune 220g",
    "link": "https://pakeezaproducts.store/products/wow-immune-220g",
    "price": "Rs.1,800.00",
    "category": "Oral Care"
  },
  {
    "title": "WOW Immune 220g | Pack of 2",
    "link": "https://pakeezaproducts.store/products/wow-immune-220g-pack-of-2",
    "price": "Rs.3,600.00",
    "discountedPrice": "Rs.3,400.00",
    "category": "Oral Care"
  },
  {
    "title": "WOW Immune 220g | Pack of 3",
    "link": "https://pakeezaproducts.store/products/wow-immune-220g-pack-of-3",
    "price": "Rs.5,400.00",
    "discountedPrice": "Rs.5,000.00",
    "category": "Oral Care"
  }
]